<?xml version="1.0" encoding="utf-8" ?>
<dwsync>
<file name="AclComponent.php" server="saihe.sakura.ne.jp/www/" local="130861530524110788" remote="130888295400000000" />
<file name="AuthComponent.php" server="saihe.sakura.ne.jp/www/" local="130861530525100879" remote="130888295400000000" />
<file name="CookieComponent.php" server="saihe.sakura.ne.jp/www/" local="130861530525191267" remote="130888296000000000" />
<file name="EmailComponent.php" server="saihe.sakura.ne.jp/www/" local="130861530525250885" remote="130888296000000000" />
<file name="PaginatorComponent.php" server="saihe.sakura.ne.jp/www/" local="130861530525330890" remote="130888296000000000" />
<file name="RequestHandlerComponent.php" server="saihe.sakura.ne.jp/www/" local="130861530525410888" remote="130888296000000000" />
<file name="SecurityComponent.php" server="saihe.sakura.ne.jp/www/" local="130861530525580907" remote="130888296000000000" />
<file name="SessionComponent.php" server="saihe.sakura.ne.jp/www/" local="130861530525650918" remote="130888296000000000" />
</dwsync>